{"name":"07 - User success create new account from sign up page","id":"register-amazon-new-user;07---user-success-create-new-account-from-sign-up-page","testSteps":[{"number":1,"description":"Given user membuka halaman utama Amazon","duration":11941,"startTime":"2021-12-23T16:44:22.938+07:00[Asia/Jakarta]","screenshots":[{"screenshot":"265de672134434aff178c6d0ab9e56388734a1aa7ecb88fe2bcb474986a6cc42.png","timeStamp":1640252674876}],"result":"SUCCESS","precondition":false,"level":0},{"number":2,"description":"When user mengklik button account di top navigation bar","duration":3744,"startTime":"2021-12-23T16:44:34.909+07:00[Asia/Jakarta]","screenshots":[{"screenshot":"300777ddb6bb8b23597096b87fa44ffb0c5b36c84bceb467087fe6bd7334aa57.png","timeStamp":1640252678653}],"result":"SUCCESS","precondition":false,"level":0},{"number":3,"description":"And user mengklik button \u0027Create your Amazon account\u0027","duration":1810,"startTime":"2021-12-23T16:44:38.655+07:00[Asia/Jakarta]","screenshots":[{"screenshot":"7e0bac8fa424c5a82bb76897ad64e680712b0bc22afc5fd8629b7f67ad43b74c.png","timeStamp":1640252680464}],"result":"SUCCESS","precondition":false,"level":0},{"number":4,"description":"And user mengisi seluruh field sign up form dengan benar dan sesuai","duration":6500,"startTime":"2021-12-23T16:44:40.467+07:00[Asia/Jakarta]","screenshots":[{"screenshot":"f93765191f924eb6990318146153821d3cbc5fcfc41c9c2da9762cfd178a61a0.png","timeStamp":1640252686966}],"result":"SUCCESS","precondition":false,"level":0},{"number":5,"description":"Then user diarahkan ke halaman verifikasi email","duration":13,"startTime":"2021-12-23T16:44:46.969+07:00[Asia/Jakarta]","screenshots":[{"screenshot":"f93765191f924eb6990318146153821d3cbc5fcfc41c9c2da9762cfd178a61a0.png","timeStamp":1640252686981}],"result":"SUCCESS","precondition":false,"level":0}],"userStory":{"id":"register-amazon-new-user","storyName":"Register Amazon New User","path":"amazon/Sign%20Up.feature","narrative":"  As a User\n  I want to create my new account\n  So that I can access my new account and do any activities on it","type":"feature"},"featureTag":{"name":"Amazon/Register Amazon New User","type":"feature","displayName":"Amazon/Register Amazon New User"},"title":"07 - User success create new account from sign up page","description":"","tags":[{"name":"Amazon","type":"capability","displayName":"Amazon"},{"name":"Amazon/Register Amazon New User","type":"feature","displayName":"Register Amazon New User"},{"name":"DESKTOP-T16","type":"TestCaseKey","displayName":"DESKTOP-T16"},{"name":"SignUp","type":"tag","displayName":"SignUp"}],"startTime":"2021-12-23T16:44:22.928+07:00[Asia/Jakarta]","duration":24057,"projectKey":"","sessionId":"aabf0acfc46cf6886d70c894dc047fff","driver":"chrome","isManualTestingUpToDate":false,"manual":false,"testSource":"Cucumber","result":"SUCCESS"}