{"name":"02 - User can go to login page from clicking button sign in from account navigation bar dropdown menu","id":"login-amazon;02---user-can-go-to-login-page-from-clicking-button-sign-in-from-account-navigation-bar-dropdown-menu","testSteps":[{"number":1,"description":"Given user membuka halaman utama Amazon","duration":11706,"startTime":"2021-12-23T16:39:09.210+07:00[Asia/Jakarta]","screenshots":[{"screenshot":"45ee2e6a164a5600eada28dc2710b2ba35dcb52682e6ab72fba8d33a485ed9bc.png","timeStamp":1640252360915}],"result":"SUCCESS","precondition":false,"level":0},{"number":2,"description":"When user melakukan hovering mouse ke button account di top navigation bar","duration":2638,"startTime":"2021-12-23T16:39:20.920+07:00[Asia/Jakarta]","screenshots":[{"screenshot":"8d525e8e8feeb1d3d2c6b3f94ab3f2cec46ecbcd5f4243ee80e2cce8d409bf8d.png","timeStamp":1640252363554}],"result":"SUCCESS","precondition":false,"level":0},{"number":3,"description":"And user mengklik button Sign In pada account nav bar","duration":3684,"startTime":"2021-12-23T16:39:23.582+07:00[Asia/Jakarta]","screenshots":[{"screenshot":"300777ddb6bb8b23597096b87fa44ffb0c5b36c84bceb467087fe6bd7334aa57.png","timeStamp":1640252367264}],"result":"SUCCESS","precondition":false,"level":0},{"number":4,"description":"Then user akan diarahkan ke halaman utama login","duration":1352,"startTime":"2021-12-23T16:39:27.274+07:00[Asia/Jakarta]","screenshots":[{"screenshot":"300777ddb6bb8b23597096b87fa44ffb0c5b36c84bceb467087fe6bd7334aa57.png","timeStamp":1640252368625}],"result":"SUCCESS","precondition":false,"level":0}],"userStory":{"id":"login-amazon","storyName":"Login Amazon","path":"amazon/Sign%20In.feature","narrative":"  As a User\n  I want to login to my account\n  So that I can access my account and do any activities on it","type":"feature"},"featureTag":{"name":"Amazon/Login Amazon","type":"feature","displayName":"Amazon/Login Amazon"},"title":"02 - User can go to login page from clicking button sign in from account navigation bar dropdown menu","description":"","tags":[{"name":"Amazon","type":"capability","displayName":"Amazon"},{"name":"Amazon/Login Amazon","type":"feature","displayName":"Login Amazon"},{"name":"Login","type":"tag","displayName":"Login"},{"name":"DESKTOP-T2","type":"TestCaseKey","displayName":"DESKTOP-T2"}],"startTime":"2021-12-23T16:39:09.193+07:00[Asia/Jakarta]","duration":19436,"projectKey":"","sessionId":"1ca7e71879062d7fd9f68033cb232aaf","driver":"chrome","isManualTestingUpToDate":false,"manual":false,"testSource":"Cucumber","result":"SUCCESS"}